praetorian/Praetorian.py
praetorian/__init__.py
praetorian-0.1.0a0.dist-info/LICENSE
praetorian-0.1.0a0.dist-info/METADATA
praetorian-0.1.0a0.dist-info/WHEEL
praetorian-0.1.0a0.dist-info/top_level.txt
praetorian-0.1.0a0.dist-info/RECORD
