Metadata-Version: 2.1
Name: praetorian
Version: 0.1.0a0
Summary: Praetorian is a basic Sentry wrapper in Python.
Home-page: https://github.com/ThaumielSparrow/praetorian
Author: Luzhou Zhang
Author-email: lzhang1337@gmail.com
License: BSD-3-Clause
Platform: UNKNOWN
Requires-Python: >=3.6
License-File: LICENSE
